chunktopus/__init__.py
chunktopus/main.py
chunktopus/routes/__init__.py
chunktopus/routes/chunking_routes.py
chunktopus/routes/root_routes.py
chunktopus/services/chunking.py
chunktopus/utils/__init__.py
chunktopus/utils/chunking.py
chunktopus/utils/openai.py
chunktopus-0.1.2.dist-info/METADATA
chunktopus-0.1.2.dist-info/WHEEL
chunktopus-0.1.2.dist-info/entry_points.txt
chunktopus-0.1.2.dist-info/top_level.txt
chunktopus-0.1.2.dist-info/RECORD
