Metadata-Version: 2.4
Name: chunktopus
Version: 0.1.2
Summary: A multithreaded OCR API for document processing and chunking with simple interface
Home-page: https://github.com/Unsiloed-opensource/ocr-api-multithreaded
Author: Unsiloed AI
Author-email: info@unsiloed.com
Classifier: Programming Language :: Python :: 3
Classifier: License :: OSI Approved :: MIT License
Classifier: Operating System :: OS Independent
Requires-Python: >=3.8
Requires-Dist: uvicorn
Requires-Dist: fastapi
Requires-Dist: python-multipart
Requires-Dist: python-dotenv
Requires-Dist: pdf2image
Requires-Dist: Pillow
Requires-Dist: PyPDF2
Requires-Dist: python-docx
Requires-Dist: python-pptx
Requires-Dist: openai
Requires-Dist: numpy
Requires-Dist: opencv-python-headless
Requires-Dist: requests
Dynamic: author
Dynamic: author-email
Dynamic: classifier
Dynamic: description
Dynamic: description-content-type
Dynamic: home-page
Dynamic: requires-dist
Dynamic: requires-python
Dynamic: summary
